README.md
setup.py
django_opengauss_backend/base.py
django_opengauss_backend/client.py
django_opengauss_backend/compat.py
django_opengauss_backend/creation.py
django_opengauss_backend/features.py
django_opengauss_backend/introspection.py
django_opengauss_backend/operations.py
django_opengauss_backend/schema.py
django_opengauss_backend.egg-info/PKG-INFO
django_opengauss_backend.egg-info/SOURCES.txt
django_opengauss_backend.egg-info/dependency_links.txt
django_opengauss_backend.egg-info/not-zip-safe
django_opengauss_backend.egg-info/top_level.txt