Metadata-Version: 2.1
Name: django-opengauss-backend
Version: 0.4.0
Summary: openGauss database dialect for django
Home-page: https://github.com/vimiix/django-opengauss-backend
Author: Vimiix
Author-email: i@vimiix.com
License: MIT
Platform: UNKNOWN
Classifier: Development Status :: 5 - Production/Stable
Classifier: Framework :: Django
Classifier: Intended Audience :: Developers
Classifier: License :: OSI Approved :: MIT License
Classifier: Operating System :: OS Independent
Classifier: Programming Language :: Python
Classifier: Programming Language :: Python :: 3
Classifier: Topic :: Software Development :: Libraries :: Python Modules
